signalflowcli/__init__.py
signalflowcli/csvflow.py
signalflowcli/graph.py
signalflowcli/live.py
signalflowcli/prompt.py
signalflowcli/tzaction.py
signalflowcli/utils.py
signalflowcli/version.py
signalflowcli-1.3.3.dist-info/LICENSE
signalflowcli-1.3.3.dist-info/METADATA
signalflowcli-1.3.3.dist-info/WHEEL
signalflowcli-1.3.3.dist-info/entry_points.txt
signalflowcli-1.3.3.dist-info/pbr.json
signalflowcli-1.3.3.dist-info/top_level.txt
signalflowcli-1.3.3.dist-info/zip-safe
signalflowcli-1.3.3.dist-info/RECORD
