Metadata-Version: 2.1
Name: signalflowcli
Version: 1.3.3
Summary: SignalFx Python Library
Home-page: https://github.com/signalfx/signalflow-cli
Author: SignalFx, Inc
Author-email: info@signalfx.com
License: Apache Software License v2
Platform: UNKNOWN
Classifier: Operating System :: OS Independent
Classifier: Programming Language :: Python
Requires-Dist: ansicolor
Requires-Dist: pandas (>=0.18.0)
Requires-Dist: matplotlib
Requires-Dist: requests
Requires-Dist: prompt-toolkit (>=2.0.1)
Requires-Dist: pygments
Requires-Dist: pygments-signalflow (>=0.3)
Requires-Dist: signalfx (>=1.0.14)
Requires-Dist: tslib (>=1.5.1)
Requires-Dist: six (>=1.10.0)
